redeye/__init__.py
redeye/main.py
redeye-0.0.2.dist-info/DESCRIPTION.rst
redeye-0.0.2.dist-info/entry_points.txt
redeye-0.0.2.dist-info/METADATA
redeye-0.0.2.dist-info/metadata.json
redeye-0.0.2.dist-info/RECORD
redeye-0.0.2.dist-info/top_level.txt
redeye-0.0.2.dist-info/WHEEL
