Metadata-Version: 2.0
Name: redeye
Version: 0.0.2
Summary: A library to watch Redis
Home-page: https://github.com/spulec/redeye
Author: Steve Pulec
Author-email: spulec@gmail
License: Apache
Platform: UNKNOWN
Requires-Dist: redis
